team3_chassis/__init__.py
team3_chassis/utils.py
team3_chassis/database/__init__.py
team3_chassis/database/db_utils.py
team3_chassis/discovery/__init__.py
team3_chassis/discovery/consulprovider.py
team3_chassis/errormanager/__init__.py
team3_chassis/errormanager/circuitbreaker.py
team3_chassis/messaging/__init__.py
team3_chassis/messaging/eventprovider.py
team3_chassis/messaging/loggerprovider.py
team3_chassis/security/__init__.py
team3_chassis/security/middleware.py
team3_chassis/security/securityprovider.py
team3_chassis-1.4.6.dist-info/METADATA
team3_chassis-1.4.6.dist-info/WHEEL
team3_chassis-1.4.6.dist-info/top_level.txt
team3_chassis-1.4.6.dist-info/RECORD
