Metadata-Version: 2.1
Name: team3_chassis
Version: 1.4.6
Summary: A reusable library for microservices
Author: team3
Author-email: gorka.etxebarria@alumni.mondragon.edu
